lins_asana/__init__.py
lins_asana/api_asana.py
lins_asana-1.8.0.33.dist-info/METADATA
lins_asana-1.8.0.33.dist-info/WHEEL
lins_asana-1.8.0.33.dist-info/top_level.txt
lins_asana-1.8.0.33.dist-info/RECORD
