Metadata-Version: 2.1
Name: lins-asana
Version: 1.8.0.33
Summary: Classe para uso da API Asana.
Home-page: https://bitbucket.org/grupolinsferrao/pypck-lins_asana/
Author: Guilherme Severo
Author-email: guilherme@lojaspompeia.com.br
License: MIT
Platform: UNKNOWN
